{
    "asset": {
        "format": "jpg",
        "id": "27d2401353ba54ea32594e158e2902b5",
        "name": "placa485.jpg",
        "path": "file:C:/Users/WorkStation/Desktop/exemplos/placa485.jpg",
        "size": {
            "width": 461,
            "height": 346
        },
        "state": 2,
        "type": 1
    },
    "regions": [
        {
            "id": "pSy-H7cl1c",
            "type": "RECTANGLE",
            "tags": [
                "placa de veiculo"
            ],
            "boundingBox": {
                "height": 56.42461538461538,
                "width": 125.09815242494226,
                "left": 231.5646651270208,
                "top": 167.67692307692306
            },
            "points": [
                {
                    "x": 231.5646651270208,
                    "y": 167.67692307692306
                },
                {
                    "x": 356.66281755196303,
                    "y": 167.67692307692306
                },
                {
                    "x": 356.66281755196303,
                    "y": 224.10153846153844
                },
                {
                    "x": 231.5646651270208,
                    "y": 224.10153846153844
                }
            ]
        }
    ],
    "version": "2.2.0"
}