{
    "asset": {
        "format": "jpg",
        "id": "4cf7bd0e548a691ffb1d0af9a26c637d",
        "name": "placa293.jpg",
        "path": "file:C:/Users/WorkStation/Desktop/exemplos/placa293.jpg",
        "size": {
            "width": 720,
            "height": 480
        },
        "state": 2,
        "type": 1
    },
    "regions": [
        {
            "id": "rxbTsvk8kG",
            "type": "RECTANGLE",
            "tags": [
                "placa de veiculo"
            ],
            "boundingBox": {
                "height": 74.87001733102252,
                "width": 133.85681293302542,
                "left": 73.99538106235566,
                "top": 298.37521663778165
            },
            "points": [
                {
                    "x": 73.99538106235566,
                    "y": 298.37521663778165
                },
                {
                    "x": 207.85219399538107,
                    "y": 298.37521663778165
                },
                {
                    "x": 207.85219399538107,
                    "y": 373.24523396880414
                },
                {
                    "x": 73.99538106235566,
                    "y": 373.24523396880414
                }
            ]
        },
        {
            "id": "-eeX7HT8yj",
            "type": "RECTANGLE",
            "tags": [
                "placa de veiculo"
            ],
            "boundingBox": {
                "height": 44.09012131715771,
                "width": 56.53579676674365,
                "left": 522.9561200923788,
                "top": 216.01819757365683
            },
            "points": [
                {
                    "x": 522.9561200923788,
                    "y": 216.01819757365683
                },
                {
                    "x": 579.4919168591224,
                    "y": 216.01819757365683
                },
                {
                    "x": 579.4919168591224,
                    "y": 260.10831889081453
                },
                {
                    "x": 522.9561200923788,
                    "y": 260.10831889081453
                }
            ]
        }
    ],
    "version": "2.2.0"
}