{
    "asset": {
        "format": "jpg",
        "id": "ad0ee2e27733f769c56f60b4600c05e0",
        "name": "placa1654.jpg",
        "path": "file:C:/Users/WorkStation/Desktop/exemplos/placa1654.jpg",
        "size": {
            "width": 320,
            "height": 157
        },
        "state": 2,
        "type": 1
    },
    "regions": [
        {
            "id": "OnB8Ji-41H",
            "type": "RECTANGLE",
            "tags": [
                "placa de veiculo"
            ],
            "boundingBox": {
                "height": 151.1002087682672,
                "width": 307.86885245901635,
                "left": 5.9016393442622945,
                "top": 2.437760960334029
            },
            "points": [
                {
                    "x": 5.9016393442622945,
                    "y": 2.437760960334029
                },
                {
                    "x": 313.7704918032787,
                    "y": 2.437760960334029
                },
                {
                    "x": 313.7704918032787,
                    "y": 153.53796972860124
                },
                {
                    "x": 5.9016393442622945,
                    "y": 153.53796972860124
                }
            ]
        }
    ],
    "version": "2.2.0"
}