<annotation verified="yes">
    <folder>Annotation</folder>
    <filename>placa1662.jpg</filename>
    <path>OCR-PascalVOC-export/Annotations/placa1662.jpg</path>
    <source>
        <database>Unknown</database>
    </source>
    <size>
        <width>320</width>
        <height>148</height>
        <depth>3</depth>
    </size>
    <segmented>0</segmented>
    <object>
    <name>placa de veiculo</name>
    <pose>Unspecified</pose>
    <truncated>0</truncated>
    <difficult>0</difficult>
    <bndbox>
        <xmin>2.9508196721311473</xmin>
        <ymin>4.168652993348116</ymin>
        <xmax>314.0983606557377</xmax>
        <ymax>144.94914079822615</ymax>
    </bndbox>
</object>
</annotation>
