<annotation verified="yes">
    <folder>Annotation</folder>
    <filename>placa697.jpg</filename>
    <path>OCR-PascalVOC-export/Annotations/placa697.jpg</path>
    <source>
        <database>Unknown</database>
    </source>
    <size>
        <width>1280</width>
        <height>720</height>
        <depth>3</depth>
    </size>
    <segmented>0</segmented>
    <object>
    <name>placa de veiculo</name>
    <pose>Unspecified</pose>
    <truncated>0</truncated>
    <difficult>0</difficult>
    <bndbox>
        <xmin>320.7390300230947</xmin>
        <ymin>400.01026694045174</ymin>
        <xmax>548.3602771362587</xmax>
        <ymax>533.0698151950719</ymax>
    </bndbox>
</object>
</annotation>
