<annotation verified="yes">
    <folder>Annotation</folder>
    <filename>placa401.jpg</filename>
    <path>OCR-PascalVOC-export/Annotations/placa401.jpg</path>
    <source>
        <database>Unknown</database>
    </source>
    <size>
        <width>300</width>
        <height>150</height>
        <depth>3</depth>
    </size>
    <segmented>0</segmented>
    <object>
    <name>placa de veiculo</name>
    <pose>Unspecified</pose>
    <truncated>0</truncated>
    <difficult>0</difficult>
    <bndbox>
        <xmin>5.8891454965357966</xmin>
        <ymin>1.5588914549653579</ymin>
        <xmax>293.07159353348726</xmax>
        <ymax>148.09468822170902</ymax>
    </bndbox>
</object>
</annotation>
