<annotation verified="yes">
    <folder>Annotation</folder>
    <filename>placa1004.jpg</filename>
    <path>OCR-PascalVOC-export/Annotations/placa1004.jpg</path>
    <source>
        <database>Unknown</database>
    </source>
    <size>
        <width>1280</width>
        <height>720</height>
        <depth>3</depth>
    </size>
    <segmented>0</segmented>
    <object>
    <name>placa de veiculo</name>
    <pose>Unspecified</pose>
    <truncated>0</truncated>
    <difficult>0</difficult>
    <bndbox>
        <xmin>678.8877445932029</xmin>
        <ymin>226.9368131868132</ymin>
        <xmax>779.0731204943357</xmax>
        <ymax>296.8269230769231</ymax>
    </bndbox>
</object>
</annotation>
