<annotation verified="yes">
    <folder>Annotation</folder>
    <filename>placa1118.jpg</filename>
    <path>OCR-PascalVOC-export/Annotations/placa1118.jpg</path>
    <source>
        <database>Unknown</database>
    </source>
    <size>
        <width>320</width>
        <height>160</height>
        <depth>3</depth>
    </size>
    <segmented>0</segmented>
    <object>
    <name>placa de veiculo</name>
    <pose>Unspecified</pose>
    <truncated>0</truncated>
    <difficult>0</difficult>
    <bndbox>
        <xmin>1.64778578784758</xmin>
        <ymin>0.5761316872427984</ymin>
        <xmax>317.36354273944386</xmax>
        <ymax>157.9423868312757</ymax>
    </bndbox>
</object>
</annotation>
