<annotation verified="yes">
    <folder>Annotation</folder>
    <filename>placa316.jpg</filename>
    <path>OCR-PascalVOC-export/Annotations/placa316.jpg</path>
    <source>
        <database>Unknown</database>
    </source>
    <size>
        <width>320</width>
        <height>157</height>
        <depth>3</depth>
    </size>
    <segmented>0</segmented>
    <object>
    <name>placa de veiculo</name>
    <pose>Unspecified</pose>
    <truncated>0</truncated>
    <difficult>0</difficult>
    <bndbox>
        <xmin>5.912240184757506</xmin>
        <ymin>1.6450367647058823</ymin>
        <xmax>317.4133949191686</xmax>
        <ymax>156.99999999999997</ymax>
    </bndbox>
</object>
</annotation>
