<annotation verified="yes">
    <folder>Annotation</folder>
    <filename>placa762.jpg</filename>
    <path>OCR-PascalVOC-export/Annotations/placa762.jpg</path>
    <source>
        <database>Unknown</database>
    </source>
    <size>
        <width>1024</width>
        <height>640</height>
        <depth>3</depth>
    </size>
    <segmented>0</segmented>
    <object>
    <name>placa de veiculo</name>
    <pose>Unspecified</pose>
    <truncated>0</truncated>
    <difficult>0</difficult>
    <bndbox>
        <xmin>433.95842956120094</xmin>
        <ymin>313.04990757855825</ymin>
        <xmax>521.459584295612</xmax>
        <ymax>359.1866913123845</ymax>
    </bndbox>
</object>
</annotation>
