<annotation verified="yes">
    <folder>Annotation</folder>
    <filename>placa322.jpg</filename>
    <path>OCR-PascalVOC-export/Annotations/placa322.jpg</path>
    <source>
        <database>Unknown</database>
    </source>
    <size>
        <width>320</width>
        <height>162</height>
        <depth>3</depth>
    </size>
    <segmented>0</segmented>
    <object>
    <name>placa de veiculo</name>
    <pose>Unspecified</pose>
    <truncated>0</truncated>
    <difficult>0</difficult>
    <bndbox>
        <xmin>8.129330254041571</xmin>
        <ymin>1.930222602739726</ymin>
        <xmax>309.6535796766744</xmax>
        <ymax>157.64255136986299</ymax>
    </bndbox>
</object>
</annotation>
